Ardan_pencariansurat/__init__.py
Ardan_pencariansurat/surah_info.py
modulsurahdann-0.0.1.dist-info/LICENSE
modulsurahdann-0.0.1.dist-info/METADATA
modulsurahdann-0.0.1.dist-info/WHEEL
modulsurahdann-0.0.1.dist-info/top_level.txt
modulsurahdann-0.0.1.dist-info/RECORD
