Metadata-Version: 2.1
Name: modulsurahdann
Version: 0.0.1
Summary: Negara Informasi Inform Negara
Home-page: https://github.com/dannfrd/modulsurahdann
Author: ardan
Author-email: <ardanferdiansah03@gmail.com>
License: MIT
Keywords: surah,search
Classifier: Development Status :: 1 - Planning
License-File: LICENSE
